odoo/addons/pms_l10n_es/README.rst
odoo/addons/pms_l10n_es/__init__.py
odoo/addons/pms_l10n_es/__manifest__.py
odoo/addons/pms_l10n_es/data/cron_jobs.xml
odoo/addons/pms_l10n_es/data/pms.ine.tourism.type.category.csv
odoo/addons/pms_l10n_es/data/pms_data.xml
odoo/addons/pms_l10n_es/data/pms_traveler_report_notification_email_template.xml
odoo/addons/pms_l10n_es/data/queue_data.xml
odoo/addons/pms_l10n_es/data/queue_job_function_data.xml
odoo/addons/pms_l10n_es/data/res.country.state.csv
odoo/addons/pms_l10n_es/i18n/es.po
odoo/addons/pms_l10n_es/i18n/it.po
odoo/addons/pms_l10n_es/i18n/pms_l10n_es.pot
odoo/addons/pms_l10n_es/migrations/14.0.3.0.0/post-migration.py
odoo/addons/pms_l10n_es/models/__init__.py
odoo/addons/pms_l10n_es/models/pms_checkin_partner.py
odoo/addons/pms_l10n_es/models/pms_ine_tourism_type_category.py
odoo/addons/pms_l10n_es/models/pms_log_institution_traveller_report.py
odoo/addons/pms_l10n_es/models/pms_property.py
odoo/addons/pms_l10n_es/models/pms_reservation.py
odoo/addons/pms_l10n_es/models/pms_room.py
odoo/addons/pms_l10n_es/models/pms_ses_communication.py
odoo/addons/pms_l10n_es/models/res_country_state.py
odoo/addons/pms_l10n_es/models/res_partner.py
odoo/addons/pms_l10n_es/models/res_partner_id_number.py
odoo/addons/pms_l10n_es/readme/CONTRIBUTORS.rst
odoo/addons/pms_l10n_es/readme/DESCRIPTION.rst
odoo/addons/pms_l10n_es/reports/invoice.xml
odoo/addons/pms_l10n_es/security/ir.model.access.csv
odoo/addons/pms_l10n_es/static/cert.pem
odoo/addons/pms_l10n_es/static/ses_cert.pem
odoo/addons/pms_l10n_es/static/description/icon.png
odoo/addons/pms_l10n_es/static/description/index.html
odoo/addons/pms_l10n_es/static/src/pms.ine.zip.municipality.ine.relation.csv
odoo/addons/pms_l10n_es/tests/__init__.py
odoo/addons/pms_l10n_es/tests/common.py
odoo/addons/pms_l10n_es/tests/test_pms_ses_communication.py
odoo/addons/pms_l10n_es/tests/test_res_partner.py
odoo/addons/pms_l10n_es/tests/test_wizard_ine.py
odoo14_addon_pms_l10n_es-14.0.3.5.0.dist-info/METADATA
odoo14_addon_pms_l10n_es-14.0.3.5.0.dist-info/WHEEL
odoo14_addon_pms_l10n_es-14.0.3.5.0.dist-info/top_level.txt
odoo14_addon_pms_l10n_es-14.0.3.5.0.dist-info/RECORD
