Metadata-Version: 2.1
Name: odoo14-addon-pms_l10n_es
Version: 14.0.3.5.0
Summary: PMS Spanish Adaptation
Home-page: https://github.com/OCA/pms
Author: Commit [Sun], Odoo Community Association (OCA)
Author-email: support@odoo-community.org
License: AGPL-3
Classifier: Programming Language :: Python
Classifier: Framework :: Odoo
Classifier: Framework :: Odoo :: 14.0
Classifier: License :: OSI Approved :: GNU Affero General Public License v3
Requires-Python: >=3.6
Requires-Dist: bs4
Requires-Dist: odoo14-addon-base-iso3166
Requires-Dist: odoo14-addon-l10n-es-aeat
Requires-Dist: odoo14-addon-partner-contact-birthdate
Requires-Dist: odoo14-addon-partner-contact-gender
Requires-Dist: odoo14-addon-partner-contact-nationality
Requires-Dist: odoo14-addon-partner-firstname
Requires-Dist: odoo14-addon-partner-second-lastname
Requires-Dist: odoo14-addon-pms
Requires-Dist: odoo14-addon-queue-job
Requires-Dist: odoo<14.1dev,>=14.0a
Requires-Dist: pycountry
